{
  "solute": "c1ccc2c(c1)oc1ccccc12",
  "solvent": "ClC(Cl)(Cl)Cl",
  "temperature": 333.0,
  "y_true": 0.79680496680205,
  "y_pred": 0.6797686616542697,
  "abs_error": 0.1170363051477803,
  "interaction_reasoning": {
    "council_importance": {
      "MolLogP": 1.4413505792617798,
      "MolWt": 1.3419878482818604,
      "TPSA": 2.6380746364593506,
      "NumHDonors": 2.385498285293579,
      "NumHAcceptors": 2.561833620071411,
      "NumRotatableBonds": 1.9426153898239136,
      "HallKierAlpha": 2.292038917541504,
      "LabuteASA": 1.63232421875,
      "HeavyAtomCount": 1.5179271697998047,
      "NumAromaticRings": 1.6599161624908447,
      "MaxPartialCharge": 1.3633266687393188,
      "MinPartialCharge": 2.5415825843811035,
      "pred_Tm": 1.4499006271362305,
      "abraham_A": 1.6605117321014404,
      "abraham_B": 3.502624034881592,
      "abraham_S": 1.3290318250656128,
      "abraham_E": 2.195007801055908,
      "abraham_V": 2.02882981300354,
      "Acidic": 1.3879600763320923,
      "Basic": 1.6976125240325928,
      "Protic": 1.5119352340698242,
      "Polar": 1.6039789915084839,
      "Halogen": 4.532620906829834,
      "Aromatic": 1.7815115451812744
    },
    "top_interactions": [
      {
        "council_i": "HeavyAtomCount",
        "council_j": "Halogen",
        "weight": 0.46020448207855225
      },
      {
        "council_i": "MolWt",
        "council_j": "NumHDonors",
        "weight": 0.31634023785591125
      },
      {
        "council_i": "pred_Tm",
        "council_j": "Halogen",
        "weight": 0.29102030396461487
      },
      {
        "council_i": "abraham_S",
        "council_j": "Halogen",
        "weight": 0.2875015139579773
      },
      {
        "council_i": "Basic",
        "council_j": "abraham_B",
        "weight": 0.2649189829826355
      },
      {
        "council_i": "NumAromaticRings",
        "council_j": "MinPartialCharge",
        "weight": 0.25914299488067627
      },
      {
        "council_i": "abraham_B",
        "council_j": "NumHAcceptors",
        "weight": 0.256919264793396
      },
      {
        "council_i": "abraham_E",
        "council_j": "Halogen",
        "weight": 0.2568792402744293
      }
    ]
  },
  "decision_reasoning": {
    "top_features": [
      {
        "name": "Solute_TPSA",
        "shap": 0.24877974181325974
      },
      {
        "name": "Solute_NumHeteroatoms",
        "shap": 0.16275513890813448
      },
      {
        "name": "T_inv",
        "shap": 0.14227382169897054
      },
      {
        "name": "T",
        "shap": 0.1422710892555083
      },
      {
        "name": "Solute_MolLogP",
        "shap": 0.13252568403123197
      },
      {
        "name": "Solute_fr_bicyclic",
        "shap": -0.06473641765761429
      },
      {
        "name": "Solvent_MaxPartialCharge",
        "shap": 0.06463478710703716
      },
      {
        "name": "Solute_NOCount",
        "shap": 0.06133151385223667
      },
      {
        "name": "Solute_abraham_A",
        "shap": 0.05956993156868123
      },
      {
        "name": "Solute_NHOHCount",
        "shap": 0.04965443397252741
      }
    ],
    "group_contributions": {
      "Solute": 1.2727943370445776,
      "Solvent": 0.12041698558497552,
      "Interact": -0.010664211921509717,
      "Thermo": 0.29160481750004796
    },
    "leaf_path": [
      220,
      60,
      124,
      156,
      54,
      44,
      87,
      28,
      252,
      150,
      44,
      108,
      188,
      60,
      188,
      68,
      44,
      132,
      68,
      56,
      56,
      188,
      20,
      31,
      192,
      126,
      232,
      233,
      124,
      188,
      98,
      34,
      47,
      53,
      57,
      24,
      0,
      4,
      120,
      61,
      202,
      180,
      76,
      61,
      34,
      80,
      196,
      216,
      4,
      204,
      143,
      133,
      4,
      192,
      32,
      132,
      136,
      153,
      140,
      232,
      32,
      140,
      172,
      60,
      153,
      24,
      32,
      18,
      121,
      130,
      101,
      176,
      89,
      104,
      113,
      168,
      62,
      30,
      48,
      2,
      32,
      192,
      200,
      140,
      100,
      86,
      218,
      78,
      0,
      72,
      224,
      200,
      64,
      7,
      36,
      128,
      101,
      224,
      200,
      83,
      114,
      160,
      192,
      166,
      122,
      194,
      48,
      148,
      113,
      89,
      113,
      99,
      48,
      104,
      80,
      131,
      6,
      8,
      160,
      3,
      64,
      164,
      9,
      71,
      133,
      9,
      141,
      100,
      64,
      16,
      33,
      144,
      14,
      8,
      80,
      1,
      33,
      12,
      24,
      56,
      134,
      244,
      72,
      128,
      4,
      98,
      0,
      50,
      212,
      0,
      8,
      39,
      72,
      31,
      4,
      48,
      88,
      84,
      48,
      28,
      92,
      148,
      128,
      4,
      0,
      111,
      28,
      164,
      212,
      155,
      147,
      96,
      128,
      49,
      7,
      8,
      152,
      80,
      181,
      140,
      24,
      9,
      96,
      102,
      144,
      0,
      25,
      54,
      142,
      138,
      143,
      54,
      62,
      1,
      144,
      124,
      0,
      149,
      129,
      84,
      180,
      178,
      152,
      128,
      31,
      92,
      32,
      146,
      129,
      128,
      45,
      13,
      48,
      160,
      192,
      0,
      37,
      128,
      6,
      144,
      44,
      8,
      31,
      66,
      0,
      96,
      16,
      71,
      36,
      8,
      96,
      136,
      17,
      22,
      96,
      163,
      112,
      0,
      6,
      90,
      88,
      192,
      77,
      134,
      74,
      172,
      144,
      50,
      48,
      56,
      88,
      152,
      96,
      4,
      140,
      65,
      144,
      144,
      232,
      100,
      9,
      10,
      121,
      28,
      3,
      32,
      73,
      156,
      212,
      10,
      144,
      128,
      129,
      196,
      56,
      136,
      116,
      185,
      160,
      128,
      77,
      17,
      48,
      128,
      28,
      129,
      182,
      19,
      216,
      80,
      4,
      15,
      68,
      250,
      225,
      8,
      108,
      80,
      143,
      177,
      7,
      143,
      170,
      26,
      128,
      104,
      165,
      138,
      10,
      12,
      248,
      78,
      88,
      108,
      136,
      84,
      31,
      128,
      101,
      112,
      129,
      42,
      176,
      145,
      0,
      5,
      176,
      209,
      154,
      2,
      8,
      0,
      38,
      12,
      136,
      70,
      14,
      32,
      48,
      172,
      14,
      142,
      64,
      0,
      32,
      187,
      38,
      128,
      96,
      6,
      64,
      0,
      206,
      0,
      146,
      76,
      2,
      96,
      1,
      72,
      29,
      0,
      152,
      136,
      249,
      48,
      114,
      194,
      8,
      197,
      192,
      133,
      5,
      116,
      197,
      96,
      192,
      163,
      0,
      2,
      64,
      138,
      25,
      242,
      176,
      152,
      161,
      6,
      10,
      12,
      0,
      61,
      36,
      105,
      129,
      194,
      132,
      12,
      73,
      107,
      140,
      161,
      202,
      109,
      4,
      14,
      50,
      32,
      0,
      12,
      103,
      73,
      6,
      10,
      136,
      4,
      130,
      31,
      132,
      6,
      96,
      134,
      162,
      192,
      0,
      13,
      96,
      48,
      128,
      39,
      64,
      178,
      104,
      128,
      193,
      24,
      48,
      168,
      133,
      5,
      24,
      134,
      160,
      32,
      16,
      61,
      24,
      55,
      153,
      10,
      72,
      128,
      72,
      2,
      17,
      0,
      204,
      192,
      32,
      194,
      46,
      200,
      224,
      48,
      61,
      128,
      8,
      22,
      242,
      66,
      14,
      63,
      128,
      234,
      4,
      133,
      96,
      192,
      28,
      100,
      161,
      16,
      82,
      130,
      200,
      128,
      194,
      136,
      102,
      128,
      209,
      0,
      4,
      0,
      80,
      72,
      244,
      145,
      24,
      134,
      150,
      145,
      132,
      82,
      4,
      48,
      32,
      195,
      65,
      61,
      200,
      130,
      136,
      177,
      16,
      129,
      85,
      128,
      16,
      14,
      134,
      128,
      162,
      25,
      15,
      38,
      128,
      20,
      102,
      72,
      156,
      195,
      144,
      144,
      216,
      0,
      76,
      43,
      16,
      35,
      36,
      242,
      187,
      15,
      64,
      119,
      6,
      133,
      49,
      192,
      8,
      48,
      164,
      129,
      232,
      173,
      70,
      23,
      40,
      24,
      12,
      137,
      63,
      192,
      132,
      160,
      25,
      128,
      160,
      128,
      26,
      48,
      224,
      81,
      166,
      16,
      9,
      0,
      29,
      114,
      41,
      87,
      68,
      248,
      7,
      36,
      2,
      68,
      221,
      184,
      50,
      17,
      241,
      16,
      16,
      89,
      68,
      64,
      41,
      172,
      32,
      72,
      25,
      59,
      11,
      199,
      30,
      77,
      4,
      80,
      36,
      43,
      155,
      17,
      8,
      52,
      96,
      88,
      104,
      9,
      35,
      128,
      9,
      120,
      81,
      0,
      20,
      140,
      184,
      24,
      224,
      17,
      119,
      51,
      145,
      132,
      193,
      99,
      184,
      64,
      32,
      95,
      64,
      16,
      119,
      108,
      65,
      152,
      40,
      15,
      50,
      64,
      153,
      80,
      30,
      87,
      4,
      62,
      20,
      234,
      0,
      4,
      51,
      109,
      63,
      88,
      12,
      128,
      28,
      64,
      132,
      160,
      0,
      116,
      247,
      52,
      139,
      144,
      224,
      0,
      23,
      64,
      162,
      72,
      17,
      56,
      20,
      1,
      23,
      56,
      46,
      83,
      105,
      64,
      1,
      161,
      198,
      145,
      211,
      26,
      0,
      151,
      34,
      104,
      4,
      247,
      29,
      36,
      0,
      233,
      113,
      13,
      9,
      200,
      100,
      103,
      16,
      0,
      36,
      64,
      225,
      136,
      64,
      139,
      112,
      8,
      1,
      148,
      15,
      4,
      4,
      83,
      119,
      139,
      57,
      113,
      212,
      95,
      75,
      40,
      48,
      200,
      132,
      21,
      4,
      177,
      189,
      178,
      128,
      223,
      224,
      225,
      27,
      160,
      56,
      128,
      12,
      13,
      136,
      49,
      64,
      28,
      160,
      49,
      229,
      44,
      0,
      49,
      63,
      204,
      144,
      13,
      172,
      100,
      8,
      108,
      96,
      244,
      200,
      111,
      106,
      188,
      56,
      65,
      145,
      207,
      0,
      32,
      22,
      232,
      0,
      46,
      143,
      225,
      48,
      59,
      95,
      128,
      240,
      0,
      17,
      183,
      216,
      64,
      17,
      0,
      25,
      137,
      228,
      64,
      0,
      42,
      63,
      1,
      66,
      192,
      1,
      128,
      32,
      44,
      25,
      0,
      63,
      21,
      216,
      0,
      188,
      59,
      152,
      78,
      59,
      168,
      148,
      183,
      65,
      68,
      1,
      128,
      132,
      239,
      224,
      113,
      114,
      52,
      155,
      188,
      104,
      150,
      135,
      169,
      178,
      240,
      40,
      184,
      224,
      136,
      128,
      100,
      225,
      136,
      5,
      148,
      68,
      152,
      30,
      104,
      9,
      15,
      196,
      184,
      167,
      150,
      24,
      87,
      236,
      3,
      40,
      39,
      176,
      196,
      208,
      120,
      174,
      16,
      20,
      0,
      194,
      200,
      185,
      207,
      148,
      132,
      88,
      240,
      1,
      130,
      104,
      178,
      119,
      59,
      77,
      224,
      31,
      80,
      132,
      8,
      37,
      241,
      13,
      225,
      88,
      239,
      160,
      17,
      88,
      32,
      5,
      138,
      164,
      50,
      24,
      4,
      128,
      17,
      110,
      243,
      94,
      128,
      96,
      76,
      0,
      121,
      76,
      20,
      22,
      129,
      1,
      151,
      8,
      37,
      144,
      19,
      145,
      193,
      8,
      145,
      136,
      111,
      5,
      202,
      8,
      157,
      115,
      120,
      36,
      207,
      20,
      151,
      48,
      12,
      159,
      110,
      99,
      171,
      243,
      36,
      198,
      85,
      115,
      163,
      38,
      8,
      58,
      64,
      122,
      40,
      176,
      193,
      40,
      177,
      5,
      40,
      1,
      112,
      0,
      49,
      224,
      128,
      44,
      64,
      59,
      1,
      128,
      194,
      68,
      96,
      8,
      39,
      108,
      112,
      51,
      183,
      51,
      192,
      48,
      27,
      20,
      12,
      204,
      207,
      172,
      103,
      86,
      29,
      48,
      192,
      16,
      4,
      112,
      0,
      60,
      21,
      80,
      196,
      105,
      162,
      128,
      251,
      28,
      195,
      16,
      137,
      48,
      91,
      157,
      130,
      177,
      0,
      34,
      116,
      56,
      66,
      197,
      84,
      165,
      131,
      131,
      248,
      156,
      192,
      148,
      244,
      32,
      37,
      152,
      48,
      24,
      160,
      25,
      8,
      19,
      16,
      2,
      176,
      16,
      64,
      64,
      183,
      205,
      29,
      5,
      100,
      163,
      65,
      64,
      38,
      152,
      0,
      198,
      12,
      66,
      138,
      77,
      128,
      144,
      13,
      4,
      64,
      75,
      45,
      164,
      72,
      128,
      12,
      176,
      168,
      0,
      91,
      84,
      16,
      110,
      168,
      72,
      225,
      192,
      80,
      78,
      170,
      2,
      20,
      164,
      228,
      130,
      16,
      70,
      140,
      69,
      28,
      133,
      103,
      16,
      155,
      2,
      152,
      183,
      40,
      13,
      84,
      67,
      56,
      232,
      92,
      249,
      140,
      2,
      28,
      224,
      199,
      136,
      64,
      71,
      45,
      45,
      84,
      32,
      198,
      96,
      14,
      147,
      217,
      20,
      71,
      28,
      100,
      14,
      76,
      192,
      232,
      192,
      68,
      17,
      128,
      200,
      204,
      3,
      5,
      120,
      11,
      5,
      8,
      154,
      164,
      4,
      108,
      120,
      119,
      80,
      8,
      97,
      8,
      40,
      144,
      180,
      172,
      77,
      24,
      79,
      68,
      44,
      0,
      97,
      13,
      168,
      106,
      13,
      25,
      136,
      51,
      165,
      61,
      9,
      88,
      128,
      12,
      184,
      93,
      178,
      220,
      39,
      104,
      56,
      131,
      5,
      136,
      13,
      40,
      0,
      64,
      168,
      109,
      157,
      13,
      162,
      240,
      4,
      200,
      29,
      152,
      13,
      77,
      225,
      140,
      16,
      69,
      32,
      224,
      0,
      201,
      8,
      129,
      128,
      236,
      4,
      176,
      80,
      128,
      72,
      77,
      13,
      236,
      60,
      84,
      247,
      133,
      117,
      43,
      133,
      146,
      67,
      102,
      51,
      138,
      251,
      166,
      80,
      108,
      32,
      12,
      120,
      72,
      230,
      164,
      102,
      66,
      4,
      24,
      162,
      56,
      44,
      16,
      140,
      23,
      48,
      24,
      68,
      16,
      128,
      50,
      198,
      16,
      88,
      65,
      45,
      57,
      123,
      102,
      3,
      209,
      176,
      8,
      88,
      146,
      6,
      199,
      132,
      128,
      114,
      52,
      212,
      160,
      192,
      65,
      128,
      152,
      208,
      13,
      66,
      127,
      37,
      37,
      210,
      140,
      4,
      27,
      17,
      152,
      120,
      56,
      205,
      205,
      182,
      160,
      113,
      12,
      200,
      79,
      156,
      196,
      191,
      170,
      228,
      25,
      42,
      171,
      41,
      0,
      37,
      64,
      44,
      70,
      73,
      133,
      208,
      213,
      13,
      202,
      176,
      16,
      88,
      200,
      200,
      226,
      157,
      12,
      200,
      0,
      66,
      192,
      204,
      160,
      40,
      64,
      105,
      51,
      197,
      8,
      16,
      109,
      248,
      32,
      142,
      56,
      57,
      43,
      149,
      112,
      80,
      166,
      39,
      24,
      76,
      124,
      64,
      184,
      205,
      96,
      2,
      59,
      19,
      15,
      176,
      16,
      136,
      133,
      148,
      68,
      70,
      192,
      3,
      144,
      47,
      155,
      132,
      11,
      32,
      132,
      88,
      8,
      80,
      16,
      80,
      183,
      55,
      64,
      33,
      4,
      41,
      222,
      200,
      155,
      45,
      144,
      141,
      226,
      0,
      65,
      106,
      160,
      184,
      109,
      4,
      196,
      183,
      211,
      16,
      172,
      118,
      32,
      172,
      40,
      101,
      28,
      22,
      51,
      177,
      179,
      164,
      8,
      90,
      131,
      2,
      14,
      96,
      4,
      113,
      8,
      128,
      35,
      217,
      136,
      71,
      216,
      4,
      114,
      48,
      18,
      192,
      144,
      25,
      22,
      115,
      168,
      176,
      15,
      220,
      29,
      128,
      230,
      0,
      41,
      80,
      7,
      230,
      208,
      226,
      32,
      152,
      88,
      196,
      72,
      219,
      140,
      128,
      233,
      120,
      192,
      144,
      144,
      121,
      72,
      77,
      48,
      73,
      212,
      66,
      44,
      102,
      212,
      192,
      236,
      179,
      249,
      145,
      48,
      158,
      84,
      155,
      4,
      116,
      197,
      148,
      32,
      96,
      6,
      56,
      0,
      72,
      4,
      5,
      204,
      109,
      96,
      224,
      136,
      228,
      8,
      121,
      61,
      144,
      59,
      248,
      94,
      68,
      88,
      66,
      40,
      58,
      81,
      128,
      13,
      75,
      242,
      8,
      136,
      83,
      23,
      57,
      128,
      160,
      219,
      120,
      41,
      0,
      150,
      16,
      98,
      140,
      96,
      168,
      175,
      59,
      134,
      80,
      179,
      40,
      128,
      108,
      112,
      208,
      66,
      12,
      51,
      132,
      2,
      138,
      248,
      34,
      64,
      32,
      38,
      27,
      13,
      165,
      2,
      40,
      163,
      80,
      190,
      26,
      184,
      3,
      109,
      8,
      22,
      114,
      66,
      19,
      249,
      38,
      81,
      4,
      208,
      112,
      184,
      96,
      240,
      32,
      28,
      216,
      12,
      169,
      21,
      208,
      146,
      75,
      48,
      232,
      28,
      108,
      0,
      11,
      69,
      130,
      141,
      212,
      88,
      236,
      51,
      190,
      38,
      97,
      36,
      51,
      160,
      0,
      149,
      120,
      152,
      83,
      12,
      72,
      52,
      7,
      204,
      125,
      33,
      11,
      40,
      231,
      152,
      82,
      99,
      224,
      177,
      170,
      61,
      144,
      36,
      96,
      24,
      128,
      210,
      135,
      45,
      38,
      168,
      65,
      81,
      77,
      64,
      114,
      187,
      144,
      228,
      160,
      4,
      40,
      49,
      112,
      0,
      17,
      20,
      5,
      184,
      144,
      168,
      99,
      48,
      131,
      96,
      136,
      80,
      64,
      34,
      74,
      208,
      19,
      96,
      249,
      22,
      162,
      60,
      36,
      139,
      117,
      0,
      169,
      224,
      33,
      12,
      24,
      168,
      132,
      220,
      3,
      70,
      64,
      67,
      64,
      204,
      124,
      40,
      25,
      136,
      121,
      176,
      48,
      168,
      128,
      1,
      162,
      48,
      102,
      32,
      120,
      120,
      0,
      156,
      165,
      210,
      38,
      1,
      172,
      16,
      136,
      120,
      0,
      41,
      35,
      192,
      237,
      136,
      32,
      39,
      0,
      47,
      120,
      8,
      180,
      104,
      56,
      226,
      130,
      162,
      118,
      194,
      182,
      216,
      16,
      8,
      163,
      145,
      84,
      188,
      218,
      16,
      6,
      101,
      160,
      2,
      44,
      152,
      2,
      84,
      106,
      18,
      32,
      224,
      4,
      60,
      4,
      134,
      7,
      194,
      62,
      72,
      210,
      204,
      202,
      128,
      178,
      129,
      84,
      122,
      2,
      146,
      22,
      89,
      128,
      224,
      160,
      15,
      0,
      11,
      64,
      79,
      44,
      193,
      2,
      67,
      71,
      123,
      176,
      128,
      83,
      24,
      20,
      32,
      15,
      117,
      182,
      20,
      61,
      207,
      71,
      11,
      83,
      204,
      32,
      0,
      60,
      12,
      74,
      164,
      40,
      192,
      232,
      130,
      62,
      56,
      123,
      5,
      146,
      17,
      105,
      184,
      120,
      120,
      197,
      38,
      16,
      2,
      0,
      121,
      139,
      39,
      49,
      7,
      192,
      44,
      35,
      18,
      13,
      185,
      120,
      72,
      161,
      145,
      32,
      152,
      68,
      223,
      192,
      192,
      136,
      128,
      136,
      130,
      176,
      12,
      140,
      241,
      0,
      3,
      82,
      238,
      14,
      249,
      191,
      104,
      209,
      15,
      21,
      208,
      9,
      125,
      39,
      192,
      19,
      104,
      128,
      51,
      190,
      84,
      132,
      198,
      49,
      64,
      210,
      224,
      39,
      114,
      40,
      121,
      128,
      68,
      246,
      176,
      165,
      39,
      2,
      207,
      96,
      152,
      38,
      216,
      143,
      88,
      15,
      164,
      64,
      244,
      96,
      128,
      48,
      249,
      32,
      10,
      154,
      209,
      175,
      210,
      88,
      171,
      27,
      247,
      70,
      10,
      224,
      168,
      38,
      212,
      104,
      18,
      154,
      16,
      88,
      200,
      16,
      180,
      121,
      4,
      96,
      82,
      24,
      160,
      96,
      8,
      194,
      145,
      139,
      131,
      16,
      72,
      174,
      148,
      73,
      10,
      16,
      16,
      192,
      112,
      60,
      6,
      209,
      164,
      72,
      16,
      82,
      94,
      70,
      84,
      3,
      228,
      64,
      20,
      57,
      114,
      64,
      96,
      20,
      132,
      41,
      158,
      82,
      200,
      67,
      81,
      16,
      70,
      228,
      2,
      13,
      5,
      16,
      18,
      198,
      6,
      253,
      89,
      40,
      32,
      28,
      4,
      142,
      56,
      144,
      39,
      168,
      38,
      97,
      230,
      40,
      26,
      13,
      138,
      66,
      88,
      200,
      91,
      57,
      120,
      48,
      176,
      250,
      36,
      5,
      117,
      143,
      192,
      27,
      32,
      128,
      64,
      66,
      230,
      94,
      148,
      19,
      152,
      175,
      28,
      49,
      7,
      0,
      206,
      216,
      96,
      34,
      88,
      211,
      32,
      120,
      145,
      88,
      137,
      184,
      180,
      64,
      224,
      58,
      4,
      210,
      32,
      86,
      140,
      28,
      20,
      207,
      94,
      132,
      38,
      38,
      139,
      66,
      224,
      40,
      248,
      162,
      21,
      244,
      24,
      0,
      174,
      120,
      8,
      32,
      70,
      136,
      64,
      148,
      24,
      104,
      8,
      76,
      17,
      208,
      118,
      170,
      2,
      8,
      168,
      135,
      200,
      210,
      64,
      39,
      17,
      213,
      55,
      131,
      216,
      228,
      215,
      48,
      189,
      15,
      80,
      6,
      0,
      18,
      224,
      16,
      144,
      179,
      8,
      34,
      42,
      0,
      52,
      174,
      129,
      241,
      156,
      138,
      79,
      173,
      30,
      10,
      111,
      143,
      138,
      37,
      103,
      8,
      68,
      40,
      32,
      64,
      192,
      200,
      8,
      39,
      5,
      181,
      118,
      121,
      153,
      160,
      56,
      16,
      38,
      8,
      72,
      233,
      10,
      224,
      61,
      112,
      104,
      176,
      19,
      64,
      39,
      226,
      14,
      6,
      40,
      140,
      224,
      3,
      32,
      16,
      133,
      0,
      128,
      47,
      132,
      24,
      200,
      250,
      0,
      240,
      144,
      40,
      0,
      100,
      184,
      88,
      101,
      1,
      206,
      169,
      42,
      202,
      64,
      128,
      12,
      27,
      16,
      210,
      158,
      250,
      32,
      144,
      57,
      13,
      16,
      68,
      91,
      132,
      209,
      19,
      134,
      120,
      7,
      23,
      207,
      24,
      197,
      200,
      144,
      192,
      4,
      16,
      190,
      8,
      209,
      92,
      176,
      94,
      195,
      0,
      72,
      204,
      19,
      16,
      208,
      206,
      248,
      72,
      41,
      64,
      232,
      164,
      57,
      34,
      140,
      66,
      218,
      91,
      52,
      144,
      199,
      128,
      135,
      210,
      98,
      156,
      53,
      128,
      72,
      193,
      100,
      32,
      34,
      7,
      192,
      0,
      130,
      144,
      103,
      23,
      226,
      16,
      0,
      83,
      162,
      128,
      98,
      142,
      144,
      24,
      55,
      80,
      12,
      192,
      15,
      208,
      97,
      16,
      200,
      16,
      9,
      151,
      64,
      130,
      78,
      225,
      80,
      0,
      249,
      0,
      42,
      34,
      36,
      167,
      109,
      233,
      91,
      192,
      132,
      128,
      32,
      68,
      19,
      183,
      40,
      48,
      35,
      70,
      13,
      200,
      81,
      16,
      51,
      146,
      39,
      161,
      33,
      27,
      140,
      23,
      118,
      4,
      168,
      28,
      24,
      176,
      8,
      112,
      226,
      165,
      84,
      230,
      0,
      64,
      51,
      98,
      112,
      136,
      59,
      95,
      115,
      62,
      167,
      177,
      79,
      52,
      16,
      60,
      49,
      68,
      95,
      37,
      220,
      237,
      200,
      15,
      132,
      99,
      44,
      56,
      15,
      250,
      50,
      80,
      1,
      48,
      45,
      80,
      201,
      32,
      168,
      133,
      8,
      8,
      93,
      248,
      8,
      176,
      18,
      199,
      4,
      3,
      57,
      225,
      132,
      101,
      102,
      10,
      195,
      143,
      90,
      28,
      136,
      225,
      156,
      16,
      35,
      129,
      232,
      32,
      73,
      200,
      16,
      80,
      160,
      36,
      245,
      39,
      85,
      106,
      103,
      125,
      134,
      249,
      0,
      82,
      39,
      116,
      10,
      220,
      234,
      42,
      192,
      8,
      0,
      159,
      144,
      136,
      48,
      190,
      25,
      14,
      173,
      102,
      13,
      72,
      160,
      16,
      151,
      115,
      3,
      91,
      64,
      15,
      28,
      64,
      192,
      248,
      70,
      24,
      194,
      158,
      232,
      144,
      7,
      120,
      104,
      128,
      121,
      158,
      78,
      4,
      24,
      130,
      111,
      80,
      146,
      184,
      86,
      1,
      22,
      20,
      32,
      203,
      135,
      176,
      6,
      12,
      8,
      128,
      24,
      120,
      210,
      209,
      210,
      74,
      226,
      50,
      179,
      12,
      1,
      75,
      144,
      149,
      206,
      16,
      35,
      112,
      176,
      249,
      76,
      48,
      40,
      120,
      219,
      190,
      37,
      0,
      144,
      63,
      143,
      8,
      32,
      114,
      156,
      12,
      14,
      176,
      10,
      232,
      80,
      16,
      200,
      167,
      128,
      46,
      0,
      9,
      128,
      116,
      142,
      13,
      200,
      157,
      167,
      16,
      38,
      80,
      0,
      7,
      50,
      72,
      128,
      0,
      8,
      181,
      40,
      102,
      147,
      1,
      96,
      64,
      32,
      171,
      128,
      160,
      19,
      52,
      23,
      83,
      50,
      0,
      15,
      225,
      39,
      160,
      72,
      181,
      153,
      135,
      133,
      252,
      64,
      38,
      218,
      32,
      15,
      136,
      128,
      138,
      11,
      148,
      26,
      0,
      83,
      126,
      16,
      54,
      35,
      50,
      0,
      200,
      128,
      252,
      144,
      64,
      174,
      39,
      92,
      8,
      8,
      161,
      155,
      160,
      42,
      176,
      152,
      132,
      163,
      156,
      4,
      110,
      213,
      7,
      200,
      42,
      195,
      15,
      8,
      28,
      176,
      20,
      110,
      144,
      128,
      42,
      89,
      106,
      204,
      13,
      211,
      32,
      55,
      166,
      16,
      51,
      15,
      147,
      36,
      117,
      0,
      16,
      135,
      8,
      115,
      18,
      0,
      170,
      28,
      121,
      143,
      112,
      96,
      176,
      41,
      123,
      38,
      233,
      42,
      147,
      180,
      121,
      89,
      194,
      19,
      42,
      104,
      64,
      80,
      19,
      83,
      15,
      203,
      155,
      64,
      32,
      242,
      78,
      192,
      123,
      103,
      162,
      0,
      155,
      32,
      193,
      60,
      39,
      69,
      243,
      0,
      136,
      153,
      7,
      157,
      165,
      131,
      61,
      45,
      140,
      40,
      29,
      14,
      200,
      163,
      224,
      118,
      28,
      108,
      220,
      142,
      24,
      4,
      80,
      224,
      231,
      103,
      8,
      110,
      1,
      169,
      128,
      40,
      143,
      45,
      8,
      80,
      249,
      244,
      160,
      170,
      228,
      130,
      48,
      172,
      19,
      28,
      64,
      0,
      44,
      15,
      241,
      81,
      130,
      116,
      160,
      33,
      48,
      93,
      29,
      65,
      106,
      64,
      175,
      65,
      32,
      56,
      204,
      200,
      60,
      208,
      18,
      103,
      8,
      2,
      80,
      57,
      249,
      41,
      3,
      192,
      226,
      93,
      135,
      128,
      24,
      50,
      72,
      192,
      48,
      118,
      6,
      167,
      16,
      8,
      128,
      6,
      226,
      29,
      140,
      10,
      129,
      94,
      83,
      209,
      104,
      65,
      48,
      5,
      167,
      135,
      45,
      24,
      88,
      21,
      243,
      0,
      64,
      40,
      173,
      224,
      131,
      220,
      200,
      0,
      215,
      24,
      210,
      189,
      6,
      8,
      175,
      214,
      6,
      68,
      166,
      16,
      134,
      1,
      8,
      113,
      16,
      28,
      166,
      8,
      6,
      7,
      214,
      133,
      128,
      137,
      150,
      183,
      0,
      157,
      130,
      0,
      144,
      96,
      19,
      26,
      8,
      0,
      227,
      38,
      115,
      239,
      96,
      47,
      0,
      184,
      83,
      61,
      1,
      32,
      59,
      63,
      188,
      200,
      49,
      232,
      26,
      43,
      111,
      164,
      15,
      96,
      48,
      6,
      141,
      232,
      16,
      120,
      210,
      141,
      70,
      224,
      128,
      180,
      128,
      31,
      9,
      206,
      32,
      160,
      224,
      69,
      78,
      96,
      98,
      84,
      6,
      0,
      6,
      114,
      64,
      64,
      144,
      14,
      32,
      159,
      170,
      71,
      38,
      88,
      176,
      0,
      85,
      43,
      39,
      121,
      70,
      136,
      111
    ]
  }
}